tweepy_trc/__init__.py
tweepy_trc/__version__.py
tweepy_trc/config.py
tweepy_trc/models.py
tweepy_trc/utils.py
tweepy_trc-0.2.5.dist-info/LICENSE
tweepy_trc-0.2.5.dist-info/METADATA
tweepy_trc-0.2.5.dist-info/WHEEL
tweepy_trc-0.2.5.dist-info/top_level.txt
tweepy_trc-0.2.5.dist-info/RECORD
