Metadata-Version: 2.1
Name: tweepy-trc
Version: 0.2.5
Summary: Integrates .trc / .twurlrc credentials into Tweepy
Home-page: https://github.com/palevell/tweepy-trc
Author: Patrick A. Levell
Author-email: patrick29501@gmx.com
License: MIT
Keywords: Tweepy,twurl,t
Platform: UNKNOWN
Classifier: Intended Audience :: Developers
Classifier: Natural Language :: English
Classifier: Programming Language :: Python
Classifier: Programming Language :: Python :: 3
Classifier: Programming Language :: Python :: 3.6
Classifier: Programming Language :: Python :: 3.7
Classifier: Programming Language :: Python :: 3.8
Classifier: License :: OSI Approved :: MIT License
Requires-Python: >=3.6
Requires-Dist: munch (>=2.3.0)
Requires-Dist: oyaml (>=0.9)
Requires-Dist: pytz (>=2019.2)
Requires-Dist: tweepy (>=3.7.0)
Requires-Dist: tzlocal (>=2.0.0)
